mixture_of_models/__init__.py
mixture_of_models-0.0.1.dist-info/licenses/LICENSE
mixture_of_models-0.0.1.dist-info/METADATA
mixture_of_models-0.0.1.dist-info/WHEEL
mixture_of_models-0.0.1.dist-info/top_level.txt
mixture_of_models-0.0.1.dist-info/RECORD
