Metadata-Version: 2.4
Name: mixture-of-models
Version: 0.0.1
Summary: Reserved namespace for a future Mixture-of-Models reasoning engine.
Author: Tyler Hughes
License: MIT
Project-URL: Homepage, https://github.com/mixture-of-models/mom
Project-URL: Source, https://github.com/mixture-of-models/mom
Classifier: Development Status :: 2 - Pre-Alpha
Classifier: Programming Language :: Python :: 3
Classifier: License :: OSI Approved :: MIT License
Requires-Python: >=3.9
License-File: LICENSE
Dynamic: license-file
